dude_pyto/__init__.py
dude_pyto/base.py
dude_pyto/context.py
dude_pyto/optional/__init__.py
dude_pyto/optional/beautifulsoup_scraper.py
dude_pyto/optional/lxml_scraper.py
dude_pyto/optional/parsel_scraper.py
dude_pyto/optional/pyppeteer_scraper.py
dude_pyto/optional/selenium_scraper.py
dude_pyto/optional/utils.py
dude_pyto/playwright_scraper.py
dude_pyto/rule.py
dude_pyto/scraped_data.py
dude_pyto/scraper.py
dude_pyto/storage.py
pydude_pyto-0.22.0.dist-info/entry_points.txt
pydude_pyto-0.22.0.dist-info/LICENSE
pydude_pyto-0.22.0.dist-info/WHEEL
pydude_pyto-0.22.0.dist-info/METADATA
pydude_pyto-0.22.0.dist-info/RECORD
