Metadata-Version: 2.1
Name: pydude-pyto
Version: 0.22.0
Summary: dude uncomplicated data extraction (For Pyto on iOS)
Home-page: https://github.com/rapjul/dude_pyto
License: AGPL-3.0-or-later
Keywords: scraping,iOS
Author: Ronie Martinez
Author-email: ronmarti18@gmail.com
Requires-Python: >=3.7,<4.0
Classifier: Development Status :: 2 - Pre-Alpha
Classifier: License :: OSI Approved :: GNU Affero General Public License v3 or later (AGPLv3+)
Classifier: Programming Language :: Python :: 3
Classifier: Programming Language :: Python :: 3.7
Classifier: Programming Language :: Python :: 3.8
Classifier: Programming Language :: Python :: 3.9
Classifier: Programming Language :: Python :: 3.10
Classifier: Programming Language :: Python :: 3
Classifier: Programming Language :: Python :: 3 :: Only
Classifier: Programming Language :: Python :: 3.10
Classifier: Programming Language :: Python :: 3.7
Classifier: Programming Language :: Python :: 3.8
Classifier: Programming Language :: Python :: 3.9
Classifier: Programming Language :: Python :: Implementation :: CPython
Classifier: Topic :: Software Development :: Libraries :: Python Modules
Provides-Extra: bs4
Provides-Extra: lxml
Provides-Extra: pyppeteer
Provides-Extra: selenium
Requires-Dist: PyYAML (>=6.0,<7.0)
Requires-Dist: beautifulsoup4 (>=4.10.0,<5.0.0); extra == "bs4"
Requires-Dist: cssselect (>=1.1.0,<2.0.0); extra == "lxml"
Requires-Dist: httpx (>=0.22,<0.24); extra == "bs4" or extra == "lxml"
Requires-Dist: lxml (>=4.8.0,<5.0.0); extra == "lxml"
Requires-Dist: parsel (>=1.6.0,<2.0.0)
Requires-Dist: pybrowsers (>=0.4.1,<0.6.0); extra == "selenium"
Requires-Dist: pyppeteer (>=1.0.2,<2.0.0); extra == "pyppeteer"
Requires-Dist: selenium-wire (>=4.6.2,<5.0.0); extra == "selenium"
Requires-Dist: webdriver-manager (>=3.7.0,<4.0.0); extra == "selenium"
Project-URL: Documentation, https://roniemartinez.github.io/dude/
Project-URL: Donate, https://github.com/sponsors/roniemartinez
Project-URL: Repository, https://github.com/rapjul/dude_pyto
